PyWebValidators/__init__.py
PyWebValidators/fileValidators.py
PyWebValidators/miscValidators.py
PyWebValidators/textValidators.py
tests/__init__.py
tests/test_validators.py
PyWebValidators-0.0.1.dist-info/METADATA
PyWebValidators-0.0.1.dist-info/WHEEL
PyWebValidators-0.0.1.dist-info/top_level.txt
PyWebValidators-0.0.1.dist-info/RECORD
