Metadata-Version: 2.1
Name: PyWebValidators
Version: 0.0.1
Summary: Validator Package for Texts and Files
Home-page: UNKNOWN
Author: tombstoneGhost (Simardeep Singh)
License: UNKNOWN
Keywords: python,validator,security,validation
Platform: UNKNOWN
Classifier: Development Status :: 1 - Planning
Classifier: Intended Audience :: Developers
Classifier: Programming Language :: Python :: 3
Classifier: Operating System :: Unix
Classifier: Operating System :: MacOS :: MacOS X
Classifier: Operating System :: Microsoft :: Windows
